gsheet_plotter/__init__.py
gsheet_plotter/gsheet_plotter.py
gsheet_plotter-0.0.1.dist-info/LICENSE
gsheet_plotter-0.0.1.dist-info/METADATA
gsheet_plotter-0.0.1.dist-info/WHEEL
gsheet_plotter-0.0.1.dist-info/top_level.txt
gsheet_plotter-0.0.1.dist-info/RECORD
