Metadata-Version: 2.1
Name: gsheet-plotter
Version: 0.0.1
Summary: A visualisation library written in Python to plot your Google Sheets.
Home-page: https://github.com/Nitika-kamboj/gsheet_plotter
Author: Nitika Kamboj
Author-email: nitika.kamboj92@gmail.com
License: UNKNOWN
Keywords: google sheet api pandas dataframe matplotlib
Platform: UNKNOWN
Classifier: Programming Language :: Python :: 3
Classifier: License :: OSI Approved :: MIT License
Classifier: Operating System :: OS Independent
Requires-Python: >=3.6
Requires-Dist: pandas
Requires-Dist: matplotlib
Requires-Dist: gsheet-api
